gcl_language_server/__init__.py
gcl_language_server/gclserver.py
gcl_language_server/main.py
gcl_language_server-0.1.dist-info/DESCRIPTION.rst
gcl_language_server-0.1.dist-info/METADATA
gcl_language_server-0.1.dist-info/RECORD
gcl_language_server-0.1.dist-info/WHEEL
gcl_language_server-0.1.dist-info/entry_points.txt
gcl_language_server-0.1.dist-info/metadata.json
gcl_language_server-0.1.dist-info/top_level.txt
