Metadata-Version: 2.0
Name: gcl-language-server
Version: 0.1
Summary: Languagage Server for Generic Configuration Language
Home-page: https://github.com/rix0rrr/gcl-language-server
Author: Rico Huijbers
Author-email: rix0rrr@gmail.com
License: MIT
Keywords: configuration
Platform: UNKNOWN
Classifier: Development Status :: 3 - Alpha
Classifier: Intended Audience :: Developers
Classifier: Topic :: Software Development :: Interpreters
Classifier: License :: OSI Approved :: MIT License
Classifier: Programming Language :: Python :: 2
Classifier: Programming Language :: Python :: 2.6
Classifier: Programming Language :: Python :: 2.7
Classifier: Programming Language :: Python :: 3
Classifier: Programming Language :: Python :: 3.2
Classifier: Programming Language :: Python :: 3.3
Classifier: Programming Language :: Python :: 3.4
Requires-Dist: gcl (>=0.6.9)
Requires-Dist: json-rpc (==1.10.3)
